<?xml version="1.0" encoding="UTF-8"?>
<DCOPData Version="1.0" Time="Wed Dec 1 08:26:09 2021" Simulator="hpeesofsim">
 <Controller name="HB1">
  <SweepCondition>
   <P>P_avs_dBm: -1.0000000000000000e+01</P>
   <P>freq: 0.0000000000000000e+00</P>
  </SweepCondition>
  <DC_OPDeclaration/>
  <DC_Voltages>
   <V>0: 0.0000000000000000e+00</V>
   <V>M2.P1: 4.7999999999999998e+00</V>
   <V>M2.P2: -2.5000000000000000e+00</V>
   <V>M2.P3: 0.0000000000000000e+00</V>
   <V>N__0: 4.7999999999999998e+00</V>
   <V>N__1: -2.5000000000000000e+00</V>
   <V>N__11: 4.7999999999999998e+00</V>
   <V>N__12: 4.7999999999999998e+00</V>
   <V>N__5: -2.5000000000000000e+00</V>
   <V>N__6: 0.0000000000000000e+00</V>
   <V>N__8: 0.0000000000000000e+00</V>
   <V>V_L: 0.0000000000000000e+00</V>
   <V>V_ds: 4.7999999999999998e+00</V>
   <V>V_in: 0.0000000000000000e+00</V>
   <GV>0: 0.0000000000000000e+00</GV>
  </DC_Voltages>
  <DC_PinCurrents>
   <I>C1: 0.0000000000000000e+00, 0.0000000000000000e+00</I>
   <I>DC_Block1: 0.0000000000000000e+00, 0.0000000000000000e+00</I>
   <I>DC_Block2: 0.0000000000000000e+00, 0.0000000000000000e+00</I>
   <I>DC_Feed1: 0.0000000000000000e+00, 0.0000000000000000e+00</I>
   <I>I_L: 0.0000000000000000e+00, 0.0000000000000000e+00</I>
   <I>I_ds: 0.0000000000000000e+00, 0.0000000000000000e+00</I>
   <I>I_in: 0.0000000000000000e+00, 0.0000000000000000e+00</I>
   <I>I_supply: -2.7940050273184318e-12, 2.7940050273184318e-12</I>
   <I>M2: 0.0000000000000000e+00, 0.0000000000000000e+00, 0.0000000000000000e+00</I>
   <I>M2.FET1: 0.0000000000000000e+00, 0.0000000000000000e+00, 0.0000000000000000e+00</I>
   <I>PORT1: 0.0000000000000000e+00, 0.0000000000000000e+00</I>
   <I>R_L: 0.0000000000000000e+00, 0.0000000000000000e+00</I>
   <I>SRC1: 2.7940050273184318e-12, -2.7940050273184318e-12</I>
   <I>SRC2: 0.0000000000000000e+00, 0.0000000000000000e+00</I>
   <I>TL1: -2.7940050273184318e-12, 0.0000000000000000e+00</I>
  </DC_PinCurrents>
  <DC_OPInstances/>
 </Controller>
</DCOPData>
